bit/__init__.py
bit/base32.py
bit/base58.py
bit/cli.py
bit/constants.py
bit/crypto.py
bit/curve.py
bit/exceptions.py
bit/format.py
bit/keygen.py
bit/transaction.py
bit/utils.py
bit/wallet.py
bit/network/__init__.py
bit/network/fees.py
bit/network/meta.py
bit/network/rates.py
bit/network/services.py
tests/__init__.py
tests/samples.py
tests/test_base58.py
tests/test_curve.py
tests/test_format.py
tests/test_segwit_addr.py
tests/test_transaction.py
tests/test_utils.py
tests/test_wallet.py
tests/utils.py
tests/network/__init__.py
tests/network/test_fees.py
tests/network/test_meta.py
tests/network/test_rates.py
tests/network/test_services.py
bit-0.8.0.dist-info/AUTHORS.rst
bit-0.8.0.dist-info/LICENSE.txt
bit-0.8.0.dist-info/METADATA
bit-0.8.0.dist-info/WHEEL
bit-0.8.0.dist-info/entry_points.txt
bit-0.8.0.dist-info/top_level.txt
bit-0.8.0.dist-info/RECORD
